text_to_sql/__init__.py
text_to_sql/database_connector.py
text_to_sql/interfaces.py
text_to_sql/main.py
text_to_sql/mock_data_generator.py
text_to_sql/utils.py
text_to_sql-0.0.6.dist-info/LICENSE
text_to_sql-0.0.6.dist-info/METADATA
text_to_sql-0.0.6.dist-info/WHEEL
text_to_sql-0.0.6.dist-info/entry_points.txt
text_to_sql-0.0.6.dist-info/top_level.txt
text_to_sql-0.0.6.dist-info/RECORD
