Metadata-Version: 2.1
Name: text-to-sql
Version: 0.0.6
Summary: A Python package which converts natural language text to PostgreSQL commands
Home-page: https://github.com/AI-Camp-Sprouts-AI/NaturalLangToSQL
Author: Vignesh Prakash
Author-email: pranomvignesh@gmail.com
License: MIT
License-File: LICENSE
Requires-Dist: langchain
Requires-Dist: langchain-experimental
Requires-Dist: openai
Requires-Dist: python-dotenv
Requires-Dist: psycopg2-binary
Requires-Dist: InquirerPy
Provides-Extra: dev
Requires-Dist: pytest ; extra == 'dev'
Requires-Dist: pytest-check ; extra == 'dev'
Requires-Dist: pytest-html ; extra == 'dev'
Requires-Dist: tqdm ; extra == 'dev'
Requires-Dist: faker ; extra == 'dev'
Requires-Dist: twine ; extra == 'dev'
